<annotation>
		<floder>JPEGImages</floder>
		<path>None</path>
		<source>
			<database>Unknow</database>
		</source>
		<segmented>0</segmented>
		<filename>火苗 (393).jpg</filename>
		<size>
			<width>275</width>
			<height>183</height>
			<depth>3</depth>
		</size>
		<object>
			<name>Fire</name>
			<pose>Unspecified</pose>
			<truncated>0</truncated>
			<difficult>0</difficult>
			<bndbox>
				<xmin>77</xmin>
				<ymin>47</ymin>
				<xmax>88</xmax>
				<ymax>74</ymax>
			</bndbox>
		</object>
		<object>
			<name>Fire</name>
			<pose>Unspecified</pose>
			<truncated>0</truncated>
			<difficult>0</difficult>
			<bndbox>
				<xmin>190</xmin>
				<ymin>38</ymin>
				<xmax>204</xmax>
				<ymax>67</ymax>
			</bndbox>
		</object>
	</annotation>